contarg/__init__.py
contarg/_version.py
contarg/hierarchical.py
contarg/utils.py
contarg/cli/__init__.py
contarg/cli/cli.py
contarg/cli/run_hierarchical.py
contarg/data/README.md
contarg/data/rois/5cmsphere_space-MNI152NLin6Asym_res-02.nii.gz
contarg/data/rois/BA46sphere_space-MNI152NLin6Asym_res-02.nii.gz
contarg/data/rois/BA46spheremasked_space-MNI152NLin6Asym_res-02.nii.gz
contarg/data/rois/BA9sphere_space-MNI152NLin6Asym_res-02.nii.gz
contarg/data/rois/DLPFCspheres_space-MNI152NLin6Asym_res-02.nii.gz
contarg/data/rois/DLPFCspheresmasked_space-MNI152NLin6Asym_res-02.nii.gz
contarg/data/rois/F3sphere_space-MNI152NLin6Asym_res-02.nii.gz
contarg/data/rois/SGCsphere_space-MNI152NLin6Asym_res-02.nii.gz
contarg/data/rois/bilateralSGCspheres_space-MNI152NLin6Asym_res-02.nii.gz
contarg/data/rois/leftSGCsphere_space-MNI152NLin6Asym_res-02.nii.gz
contarg/test/__init__.py
contarg/test/test_hierarchical.py
contarg-0.0.4.dist-info/METADATA
contarg-0.0.4.dist-info/WHEEL
contarg-0.0.4.dist-info/entry_points.txt
contarg-0.0.4.dist-info/RECORD
