Metadata-Version: 2.1
Name: contarg
Version: 0.0.4
Summary: Python package implementing/wrapping connectivity based rTMS targeting methods.
Project-URL: Homepage, https://github.com/nih-fmrif/contarg
Author-email: Dylan Nielson <adenosine@gmail.com>
License: CC)
Classifier: Programming Language :: Python :: 3
Classifier: Programming Language :: Python :: 3.8
Classifier: Programming Language :: Python :: 3.9
Classifier: Programming Language :: Python :: 3.10
Classifier: Programming Language :: Python :: 3.11
Requires-Python: >=3.8
Requires-Dist: click>=8.1.3
Requires-Dist: joblib>=1.2.0
Requires-Dist: nilearn>=0.10.0
Requires-Dist: niworkflows>=1.7.1
Requires-Dist: numpy>=1.24.1
Requires-Dist: pandas>=1.5.3
Requires-Dist: pybids==0.15.2
Requires-Dist: scikit-learn>=1.2.1
Requires-Dist: scipy>=1.10.0
Provides-Extra: dev
Requires-Dist: black~=23.1.0; extra == 'dev'
Provides-Extra: test
Requires-Dist: datalad; extra == 'test'
Requires-Dist: pytest; extra == 'test'
